README.rst
setup.py
django_acl.egg-info/PKG-INFO
django_acl.egg-info/SOURCES.txt
django_acl.egg-info/dependency_links.txt
django_acl.egg-info/requires.txt
django_acl.egg-info/top_level.txt
djangoacl/__init__.py
djangoacl/admin.py
djangoacl/models.py
djangoacl/auth/__init__.py
djangoacl/auth/backends.py
djangoacl/auth/permissions.py
djangoacl/cmsacl/__init__.py
djangoacl/cmsacl/admin.py
djangoacl/cmsacl/menu.py
djangoacl/cmsacl/middleware.py
djangoacl/cmsacl/models.py
djangoacl/cmsacl/permissions.py
djangoacl/cmsacl/migrations/0001_initial.py
djangoacl/cmsacl/migrations/__init__.py
djangoacl/migrations/0001_initial.py
djangoacl/migrations/__init__.py
tests/__init__.py
tests/manage.py
tests/settings.py
tests/urls.py
tests/backend/__init__.py
tests/backend/tests.py
tests/cmsacl/__init__.py
tests/cmsacl/tests.py